major_system/__init__.py
major_system/major_system.py
major_system/test_major_system.py
major_system/cmu_phonetic_dictionary/cmudict-0.7b
major_system-2.3.1.dist-info/LICENSE
major_system-2.3.1.dist-info/METADATA
major_system-2.3.1.dist-info/WHEEL
major_system-2.3.1.dist-info/entry_points.txt
major_system-2.3.1.dist-info/top_level.txt
major_system-2.3.1.dist-info/RECORD
